sayopy/__init__.py
sayopy/app.py
sayopy/middleware.py
sayopy/response.py
sayopy-0.1.4.dist-info/METADATA
sayopy-0.1.4.dist-info/WHEEL
sayopy-0.1.4.dist-info/top_level.txt
sayopy-0.1.4.dist-info/RECORD
