Metadata-Version: 2.1
Name: sayopy
Version: 0.1.4
Summary: Python Web Framework built for learning purposes.
Home-page: https://github.com/me/myproject
Author: Askar Saparov
Author-email: asqarsaparov2303@gmail.com
License: MIT
Classifier: License :: OSI Approved :: MIT License
Classifier: Programming Language :: Python
Classifier: Programming Language :: Python :: 3
Classifier: Programming Language :: Python :: 3.6
Classifier: Programming Language :: Python :: Implementation :: CPython
Classifier: Programming Language :: Python :: Implementation :: PyPy
Requires-Python: >=3.10.0
Requires-Dist: Jinja2 ==3.1.4
Requires-Dist: parse ==1.20.2
Requires-Dist: requests ==2.32.3
Requires-Dist: requests-wsgi-adapter ==0.4.1
Requires-Dist: WebOb ==1.8.7
Requires-Dist: whitenoise ==6.6.0
